{"name":"Successful Registration","id":"reservation-at-airbnb;successful-registration","testSteps":[{"number":1,"description":"Given John is on AirBnB \"homepage\"","duration":13301,"startTime":"2020-04-07T18:22:21.123884+03:00[Europe/Sofia]","screenshots":[{"screenshot":"94ee7ebc2709b4d21895d0e1b6944364b8be9b3137c8353b83c739283e535e2b.png","timeStamp":1586272954425}],"result":"SUCCESS","precondition":false,"level":0,"children":[{"number":2,"description":"Open: homepage","duration":12970,"startTime":"2020-04-07T18:22:21.450958200+03:00[Europe/Sofia]","screenshots":[{"screenshot":"94ee7ebc2709b4d21895d0e1b6944364b8be9b3137c8353b83c739283e535e2b.png","timeStamp":1586272954421}],"result":"SUCCESS","precondition":false,"level":1}]},{"number":3,"description":"When John submits his search details:\r\n| place | startingAfterDays | vacationDaysNumber | numberOfAdults | numberOfKids |\r\n| Bali, Indonesia | 5 | 7 | 2 | 1 |","duration":16405,"startTime":"2020-04-07T18:22:34.426568400+03:00[Europe/Sofia]","screenshots":[{"screenshot":"df205fac9b307e48189808671dda0f87f7568ec10345962fae84fece07814ad4.png","timeStamp":1586272970832}],"result":"SUCCESS","precondition":false,"level":0,"children":[{"number":4,"description":"Prepare searching details: Reservation{, place\u003d\u0027Bali, Indonesia\u0027, checkin\u003d\u00270\u0027, checkout\u003d\u00270\u0027, adults\u003d2, kids\u003d1}","duration":16280,"startTime":"2020-04-07T18:22:34.549596200+03:00[Europe/Sofia]","screenshots":[{"screenshot":"df205fac9b307e48189808671dda0f87f7568ec10345962fae84fece07814ad4.png","timeStamp":1586272970830}],"result":"SUCCESS","precondition":false,"level":1,"children":[{"number":5,"description":"Fills field with data: ReservationWidget.placeField, Bali, Indonesia","duration":2082,"startTime":"2020-04-07T18:22:34.551596600+03:00[Europe/Sofia]","screenshots":[{"screenshot":"f849437f5b748d6558f56b45f67bf0f49b7315c043fe6be85d4ededa32c62efb.png","timeStamp":1586272956634}],"result":"SUCCESS","precondition":false,"level":2},{"number":6,"description":"Clicks on: ReservationWidget.selectDestination","duration":1946,"startTime":"2020-04-07T18:22:36.636053600+03:00[Europe/Sofia]","screenshots":[{"screenshot":"fa7c9f15d0217505e3fb61ffb2b26010b1365bac65413cad5bbc5ced78e07c74.png","timeStamp":1586272958582}],"result":"SUCCESS","precondition":false,"level":2},{"number":7,"description":"Clicks on: ReservationWidget.checkinLocator","duration":1815,"startTime":"2020-04-07T18:22:38.583351100+03:00[Europe/Sofia]","screenshots":[{"screenshot":"fa7c9f15d0217505e3fb61ffb2b26010b1365bac65413cad5bbc5ced78e07c74.png","timeStamp":1586272960398}],"result":"SUCCESS","precondition":false,"level":2},{"number":8,"description":"Clicks on: ReservationWidget.checkoutLocator","duration":1838,"startTime":"2020-04-07T18:22:40.875005800+03:00[Europe/Sofia]","screenshots":[{"screenshot":"8728c3ca784cfb984f9c3c4881a89af1aa9f3437ea26efabad02a3018434fd3a.png","timeStamp":1586272962713}],"result":"SUCCESS","precondition":false,"level":2},{"number":9,"description":"Clicks on: ReservationWidget.guestsPickerDropDown","duration":1857,"startTime":"2020-04-07T18:22:42.811384200+03:00[Europe/Sofia]","screenshots":[{"screenshot":"1851ef25d17c9d63a45362d324bbf49d52539233070f882f8ecde033b556d22a.png","timeStamp":1586272964668}],"result":"SUCCESS","precondition":false,"level":2},{"number":10,"description":"Clicks on mutiple times: ReservationWidget.addAdultButton, 2","duration":1906,"startTime":"2020-04-07T18:22:44.669424100+03:00[Europe/Sofia]","screenshots":[{"screenshot":"4ff7108434a54c24656c1152e8fa20e2c0e4dc99e64e3d88a04cea0e9fc82da2.png","timeStamp":1586272966574}],"result":"SUCCESS","precondition":false,"level":2},{"number":11,"description":"Clicks on mutiple times: ReservationWidget.addKidButton, 1","duration":1823,"startTime":"2020-04-07T18:22:46.576491300+03:00[Europe/Sofia]","screenshots":[{"screenshot":"8e43c73b7f9386c83d38f8dc6ae2c14f7b9de74ab5e1e181bb4683d3a87bec2f.png","timeStamp":1586272968400}],"result":"SUCCESS","precondition":false,"level":2},{"number":12,"description":"Clicks on: ReservationWidget.saveGuestsPickerButton","duration":1819,"startTime":"2020-04-07T18:22:48.401424600+03:00[Europe/Sofia]","screenshots":[{"screenshot":"ead366b9ea6849fe3928d2530be8ec3e3efde5995021652dfecf165d8730697b.png","timeStamp":1586272970221}],"result":"SUCCESS","precondition":false,"level":2},{"number":13,"description":"Clicks on: ReservationWidget.formSubmitButton","duration":607,"startTime":"2020-04-07T18:22:50.222346400+03:00[Europe/Sofia]","screenshots":[{"screenshot":"df205fac9b307e48189808671dda0f87f7568ec10345962fae84fece07814ad4.png","timeStamp":1586272970829}],"result":"SUCCESS","precondition":false,"level":2}]}]},{"number":14,"description":"And he sets the price range from \"100\" to \"200\" levs","duration":5108,"startTime":"2020-04-07T18:22:50.833494500+03:00[Europe/Sofia]","screenshots":[{"screenshot":"33f3d7ba8863848877c8733bd42d190e54e9173c7545266fb456938ace277454.png","timeStamp":1586272975941}],"result":"SUCCESS","precondition":false,"level":0,"children":[{"number":15,"description":"Choose price range: 100, 200","duration":5106,"startTime":"2020-04-07T18:22:50.834494700+03:00[Europe/Sofia]","screenshots":[{"screenshot":"33f3d7ba8863848877c8733bd42d190e54e9173c7545266fb456938ace277454.png","timeStamp":1586272975940}],"result":"SUCCESS","precondition":false,"level":1,"children":[{"number":16,"description":"Clicks on: OffersPage.priceRangeMenuItemButton","duration":2236,"startTime":"2020-04-07T18:22:50.835494800+03:00[Europe/Sofia]","screenshots":[{"screenshot":"b15bbf82936a1438825424f54bd5f01c9831e3a5e082b4dbd0c895414108e191.png","timeStamp":1586272973072}],"result":"SUCCESS","precondition":false,"level":2},{"number":17,"description":"Fills field with data: OffersPage.fromPriceField, 100","duration":1061,"startTime":"2020-04-07T18:22:53.073344200+03:00[Europe/Sofia]","screenshots":[{"screenshot":"2dd32662b226ff5fcd0c17c6848636ae5df7e2e66e856f5ce2af1be2f1957f85.png","timeStamp":1586272974134}],"result":"SUCCESS","precondition":false,"level":2},{"number":18,"description":"Fills field with data: OffersPage.toPriceField, 200","duration":810,"startTime":"2020-04-07T18:22:54.135485300+03:00[Europe/Sofia]","screenshots":[{"screenshot":"2c4b89a7bb73998fe27483eebac2ef1df17628b267e2b9d2698eab7d4a1bb98b.png","timeStamp":1586272974945}],"result":"SUCCESS","precondition":false,"level":2},{"number":19,"description":"Clicks on: OffersPage.savePriceButton","duration":993,"startTime":"2020-04-07T18:22:54.946505+03:00[Europe/Sofia]","screenshots":[{"screenshot":"33f3d7ba8863848877c8733bd42d190e54e9173c7545266fb456938ace277454.png","timeStamp":1586272975938}],"result":"SUCCESS","precondition":false,"level":2}]}]},{"number":20,"description":"And he searches for a place with parameters:\r\n| numberOfBathrooms | airConditioner | jacuzzi |\r\n| 1 | true | true |","duration":4100,"startTime":"2020-04-07T18:22:55.942521200+03:00[Europe/Sofia]","screenshots":[{"screenshot":"f82f1b8f67ece00deb2d16131e0c2b5c0d725e9d8448a789052ce3c53205ca0a.png","timeStamp":1586272980043}],"result":"SUCCESS","precondition":false,"level":0,"children":[{"number":21,"description":"Choose more filters: entities.MoreFiltersDetails@1d6f77d7","duration":4097,"startTime":"2020-04-07T18:22:55.944521200+03:00[Europe/Sofia]","screenshots":[{"screenshot":"f82f1b8f67ece00deb2d16131e0c2b5c0d725e9d8448a789052ce3c53205ca0a.png","timeStamp":1586272980042}],"result":"SUCCESS","precondition":false,"level":1,"children":[{"number":22,"description":"Clicks on: OffersPage.moreFiltersButton","duration":1033,"startTime":"2020-04-07T18:22:55.944521200+03:00[Europe/Sofia]","screenshots":[{"screenshot":"b8c8ade99501d02d347f6f61e3574c587ba4fe87cdb01fc2c26175c655b77e58.png","timeStamp":1586272976977}],"result":"SUCCESS","precondition":false,"level":2},{"number":23,"description":"Clicks on mutiple times: MoreFiltersWidget.addBathroomButton, 1","duration":708,"startTime":"2020-04-07T18:22:56.978680200+03:00[Europe/Sofia]","screenshots":[{"screenshot":"14fe0b12078de120dec4e9f02c2eeb1d353446c50c753cad977bedcde3a33121.png","timeStamp":1586272977687}],"result":"SUCCESS","precondition":false,"level":2},{"number":24,"description":"Select filter checkbox: MoreFiltersWidget.airConditionerCheckBox, true","duration":749,"startTime":"2020-04-07T18:22:57.688346800+03:00[Europe/Sofia]","screenshots":[{"screenshot":"c5e8bb503631dd322caedd2df7472e51f0436a2c5973cbaa75214554f3cd66f6.png","timeStamp":1586272978437}],"result":"SUCCESS","precondition":false,"level":2},{"number":25,"description":"Select filter checkbox: MoreFiltersWidget.jacuzziCheckBox, true","duration":730,"startTime":"2020-04-07T18:22:58.438699500+03:00[Europe/Sofia]","screenshots":[{"screenshot":"a1ce8ccc4cfd72526ab0d4bff042d6dbc58cf6cca657b98c8482ef5ea6b7b2e4.png","timeStamp":1586272979169}],"result":"SUCCESS","precondition":false,"level":2},{"number":26,"description":"Clicks on: MoreFiltersWidget.saveMoreFiltersButton","duration":871,"startTime":"2020-04-07T18:22:59.170014100+03:00[Europe/Sofia]","screenshots":[{"screenshot":"f82f1b8f67ece00deb2d16131e0c2b5c0d725e9d8448a789052ce3c53205ca0a.png","timeStamp":1586272980041}],"result":"SUCCESS","precondition":false,"level":2}]}]},{"number":27,"description":"And he selects the \"first\" place with \"5.0\" stars","duration":1112,"startTime":"2020-04-07T18:23:00.044270900+03:00[Europe/Sofia]","exception":{"errorType":"org.openqa.selenium.StaleElementReferenceException","message":"stale element reference: element is not attached to the page document\n  (Session info: chrome\u003d80.0.3987.163)\nFor documentation on this error, please visit: https://www.seleniumhq.org/exceptions/stale_element_reference.html\nBuild info: version: \u00273.141.59\u0027, revision: \u0027e82be7d358\u0027, time: \u00272018-11-14T08:17:03\u0027\nSystem info: host: \u0027DESKTOP-JMQ6DF0\u0027, ip: \u0027192.168.1.129\u0027, os.name: \u0027Windows 10\u0027, os.arch: \u0027amd64\u0027, os.version: \u002710.0\u0027, java.version: \u002714\u0027\nDriver info: org.openqa.selenium.chrome.ChromeDriver\nCapabilities {acceptInsecureCerts: false, browserName: chrome, browserVersion: 80.0.3987.163, chrome: {chromedriverVersion: 80.0.3987.106 (f68069574609..., userDataDir: C:\\Users\\Petar\\AppData\\Loca...}, goog:chromeOptions: {debuggerAddress: localhost:55009}, javascriptEnabled: true, networkConnectionEnabled: false, pageLoadStrategy: normal, platform: WINDOWS, platformName: WINDOWS, proxy: Proxy(), setWindowRect: true, strictFileInteractability: false, timeouts: {implicit: 0, pageLoad: 300000, script: 30000}, unhandledPromptBehavior: dismiss and notify}\nSession ID: b9e93b99f2429518b73e1cb12db2ebc5\nFor documentation on this error, please visit: https://www.seleniumhq.org/exceptions/stale_element_reference.html\nBuild info: version: \u00273.141.59\u0027, revision: \u0027e82be7d358\u0027, time: \u00272018-11-14T08:17:03\u0027\nSystem info: host: \u0027DESKTOP-JMQ6DF0\u0027, ip: \u0027192.168.1.129\u0027, os.name: \u0027Windows 10\u0027, os.arch: \u0027amd64\u0027, os.version: \u002710.0\u0027, java.version: \u002714\u0027\nDriver info: driver.version: unknown","stackTrace":[{"classLoaderName":"app","declaringClass":"com.airbnb.bg.steps.libraries.ReservationActions","methodName":"selectPlaceByStarRating","fileName":"ReservationActions.java","lineNumber":68,"format":1},{"classLoaderName":"app","declaringClass":"com.airbnb.bg.steps.definitions.ReservationStepsDefinition","methodName":"selectPlaceByStar","fileName":"ReservationStepsDefinition.java","lineNumber":60,"format":1},{"declaringClass":"✽","methodName":"he selects the \"first\" place with \"5.0\" stars","fileName":"features/ReservationAirBnB.feature","lineNumber":13,"format":0}]},"result":"ERROR","precondition":false,"level":0,"children":[{"number":28,"description":"Select place by star rating: first, 5.0","duration":1102,"startTime":"2020-04-07T18:23:00.045271100+03:00[Europe/Sofia]","screenshots":[{"screenshot":"4c49d1123b67b0bd66fe74159ec22ba9b25f50422628ea7796f68cc32d2b06dd.png","htmlSource":"pagesource16376666411940234508.html.txt","timeStamp":1586272981143}],"exception":{"errorType":"org.openqa.selenium.StaleElementReferenceException","message":"stale element reference: element is not attached to the page document\n  (Session info: chrome\u003d80.0.3987.163)\nFor documentation on this error, please visit: https://www.seleniumhq.org/exceptions/stale_element_reference.html\nBuild info: version: \u00273.141.59\u0027, revision: \u0027e82be7d358\u0027, time: \u00272018-11-14T08:17:03\u0027\nSystem info: host: \u0027DESKTOP-JMQ6DF0\u0027, ip: \u0027192.168.1.129\u0027, os.name: \u0027Windows 10\u0027, os.arch: \u0027amd64\u0027, os.version: \u002710.0\u0027, java.version: \u002714\u0027\nDriver info: org.openqa.selenium.chrome.ChromeDriver\nCapabilities {acceptInsecureCerts: false, browserName: chrome, browserVersion: 80.0.3987.163, chrome: {chromedriverVersion: 80.0.3987.106 (f68069574609..., userDataDir: C:\\Users\\Petar\\AppData\\Loca...}, goog:chromeOptions: {debuggerAddress: localhost:55009}, javascriptEnabled: true, networkConnectionEnabled: false, pageLoadStrategy: normal, platform: WINDOWS, platformName: WINDOWS, proxy: Proxy(), setWindowRect: true, strictFileInteractability: false, timeouts: {implicit: 0, pageLoad: 300000, script: 30000}, unhandledPromptBehavior: dismiss and notify}\nSession ID: b9e93b99f2429518b73e1cb12db2ebc5","stackTrace":[{"classLoaderName":"app","declaringClass":"com.airbnb.bg.steps.libraries.ReservationActions","methodName":"selectPlaceByStarRating","fileName":"ReservationActions.java","lineNumber":68,"format":1},{"classLoaderName":"app","declaringClass":"com.airbnb.bg.steps.definitions.ReservationStepsDefinition","methodName":"selectPlaceByStar","fileName":"ReservationStepsDefinition.java","lineNumber":60,"format":1},{"classLoaderName":"app","declaringClass":"cucumber.runner.Runner","methodName":"runPickle","fileName":"Runner.java","lineNumber":80,"format":1}]},"result":"ERROR","precondition":false,"level":1}]},{"number":29,"description":"Then the total calculated price is according to the days","duration":1,"startTime":"2020-04-07T18:23:01.157548800+03:00[Europe/Sofia]","result":"PENDING","precondition":false,"level":0},{"number":30,"description":"And the selected period and guests number is displayed correctly","duration":1,"startTime":"2020-04-07T18:23:01.158549100+03:00[Europe/Sofia]","result":"SKIPPED","precondition":false,"level":0}],"userStory":{"id":"reservation-at-airbnb","storyName":"Reservation at AirBnB","path":"features/ReservationAirBnB.feature","type":"feature"},"featureTag":{"name":"Features/Reservation at AirBnB","type":"feature","displayName":"Features/Reservation at AirBnB"},"title":"Successful Registration","tags":[{"name":"Reservation at AirBnB","type":"feature","displayName":"Reservation at AirBnB"},{"name":"debug","type":"tag","displayName":"debug"}],"startTime":"2020-04-07T18:22:21.059869700+03:00[Europe/Sofia]","duration":40100,"testFailureCause":{"errorType":"org.openqa.selenium.StaleElementReferenceException","message":"stale element reference: element is not attached to the page document\n  (Session info: chrome\u003d80.0.3987.163)\nFor documentation on this error, please visit: https://www.seleniumhq.org/exceptions/stale_element_reference.html\nBuild info: version: \u00273.141.59\u0027, revision: \u0027e82be7d358\u0027, time: \u00272018-11-14T08:17:03\u0027\nSystem info: host: \u0027DESKTOP-JMQ6DF0\u0027, ip: \u0027192.168.1.129\u0027, os.name: \u0027Windows 10\u0027, os.arch: \u0027amd64\u0027, os.version: \u002710.0\u0027, java.version: \u002714\u0027\nDriver info: org.openqa.selenium.chrome.ChromeDriver\nCapabilities {acceptInsecureCerts: false, browserName: chrome, browserVersion: 80.0.3987.163, chrome: {chromedriverVersion: 80.0.3987.106 (f68069574609..., userDataDir: C:\\Users\\Petar\\AppData\\Loca...}, goog:chromeOptions: {debuggerAddress: localhost:55009}, javascriptEnabled: true, networkConnectionEnabled: false, pageLoadStrategy: normal, platform: WINDOWS, platformName: WINDOWS, proxy: Proxy(), setWindowRect: true, strictFileInteractability: false, timeouts: {implicit: 0, pageLoad: 300000, script: 30000}, unhandledPromptBehavior: dismiss and notify}\nSession ID: b9e93b99f2429518b73e1cb12db2ebc5","stackTrace":[{"classLoaderName":"app","declaringClass":"com.airbnb.bg.steps.libraries.ReservationActions","methodName":"selectPlaceByStarRating","fileName":"ReservationActions.java","lineNumber":68,"format":1},{"classLoaderName":"app","declaringClass":"com.airbnb.bg.steps.definitions.ReservationStepsDefinition","methodName":"selectPlaceByStar","fileName":"ReservationStepsDefinition.java","lineNumber":60,"format":1},{"classLoaderName":"app","declaringClass":"cucumber.runner.Runner","methodName":"runPickle","fileName":"Runner.java","lineNumber":80,"format":1}]},"testFailureClassname":"org.openqa.selenium.StaleElementReferenceException","testFailureMessage":"stale element reference: element is not attached to the page document\n  (Session info: chrome\u003d80.0.3987.163)\nFor documentation on this error, please visit: https://www.seleniumhq.org/exceptions/stale_element_reference.html\nBuild info: version: \u00273.141.59\u0027, revision: \u0027e82be7d358\u0027, time: \u00272018-11-14T08:17:03\u0027\nSystem info: host: \u0027DESKTOP-JMQ6DF0\u0027, ip: \u0027192.168.1.129\u0027, os.name: \u0027Windows 10\u0027, os.arch: \u0027amd64\u0027, os.version: \u002710.0\u0027, java.version: \u002714\u0027\nDriver info: org.openqa.selenium.chrome.ChromeDriver\nCapabilities {acceptInsecureCerts: false, browserName: chrome, browserVersion: 80.0.3987.163, chrome: {chromedriverVersion: 80.0.3987.106 (f68069574609..., userDataDir: C:\\Users\\Petar\\AppData\\Loca...}, goog:chromeOptions: {debuggerAddress: localhost:55009}, javascriptEnabled: true, networkConnectionEnabled: false, pageLoadStrategy: normal, platform: WINDOWS, platformName: WINDOWS, proxy: Proxy(), setWindowRect: true, strictFileInteractability: false, timeouts: {implicit: 0, pageLoad: 300000, script: 30000}, unhandledPromptBehavior: dismiss and notify}\nSession ID: b9e93b99f2429518b73e1cb12db2ebc5","testFailureSummary":"ERROR;org.openqa.selenium.StaleElementReferenceException;stale element reference: element is not attached to the page document\n  (Session info: chrome\u003d80.0.3987.163)\nFor documentation on this error, please visit: https://www.seleniumhq.org/exceptions/stale_element_reference.html\nBuild info: version: \u00273.141.59\u0027, revision: \u0027e82be7d358\u0027, time: \u00272018-11-14T08:17:03\u0027\nSystem info: host: \u0027DESKTOP-JMQ6DF0\u0027, ip: \u0027192.168.1.129\u0027, os.name: \u0027Windows 10\u0027, os.arch: \u0027amd64\u0027, os.version: \u002710.0\u0027, java.version: \u002714\u0027\nDriver info: org.openqa.selenium.chrome.ChromeDriver\nCapabilities {acceptInsecureCerts: false, browserName: chrome, browserVersion: 80.0.3987.163, chrome: {chromedriverVersion: 80.0.3987.106 (f68069574609..., userDataDir: C:\\Users\\Petar\\AppData\\Loca...}, goog:chromeOptions: {debuggerAddress: localhost:55009}, javascriptEnabled: true, networkConnectionEnabled: false, pageLoadStrategy: normal, platform: WINDOWS, platformName: WINDOWS, proxy: Proxy(), setWindowRect: true, strictFileInteractability: false, timeouts: {implicit: 0, pageLoad: 300000, script: 30000}, unhandledPromptBehavior: dismiss and notify}\nSession ID: b9e93b99f2429518b73e1cb12db2ebc5;ReservationActions.java","projectKey":"","annotatedResult":"ERROR","sessionId":"b9e93b99f2429518b73e1cb12db2ebc5","driver":"chrome","isManualTestingUpToDate":false,"manual":false,"testSource":"Cucumber","result":"ERROR"}